napari_czi_reader/__init__.py
napari_czi_reader/czi_metadata_processor.py
napari_czi_reader/czi_reader_CFIM.py
napari_czi_reader/metadata_dump.py
napari_czi_reader/napari.yaml
napari_czi_reader/library_workarounds/RangeDict.py
napari_czi_reader/library_workarounds/__init__.py
napari_czi_reader-1.2.0.dist-info/licenses/LICENSE
napari_czi_reader-1.2.0.dist-info/METADATA
napari_czi_reader-1.2.0.dist-info/WHEEL
napari_czi_reader-1.2.0.dist-info/entry_points.txt
napari_czi_reader-1.2.0.dist-info/top_level.txt
napari_czi_reader-1.2.0.dist-info/RECORD
