Metadata-Version: 2.4
Name: napari-czi-reader
Version: 1.2.0
Summary: A Czi reader plugin for napari
Home-page: https://github.com/MaxusTheOne/napari-czi-reader
Author: Markus L. Bille
Author-email: github+markus@bille.dk
License: BSD-3-Clause
Classifier: Development Status :: 2 - Pre-Alpha
Classifier: Framework :: napari
Classifier: Intended Audience :: Science/Research
Classifier: License :: OSI Approved :: BSD License
Classifier: Operating System :: OS Independent
Classifier: Programming Language :: Python
Requires-Python: >=3.9
License-File: LICENSE
Requires-Dist: aicsimageio
Requires-Dist: aicspylibczi
Requires-Dist: pint
Requires-Dist: xmltodict
Provides-Extra: test
Requires-Dist: pytest; extra == "test"
Requires-Dist: pytest-cov; extra == "test"
Requires-Dist: pytest-qt; extra == "test"
Requires-Dist: codecov; extra == "test"
Provides-Extra: dev
Requires-Dist: napari[all]; extra == "dev"
Requires-Dist: build; extra == "dev"
Requires-Dist: twine; extra == "dev"
Requires-Dist: pytest; extra == "dev"
Requires-Dist: pytest-cov; extra == "dev"
Requires-Dist: pytest-qt; extra == "dev"
Requires-Dist: codecov; extra == "dev"
Dynamic: license-file
